{
  "pid": 343680,
  "ppid": 0,
  "name": "IRRunner.exe",
  "command": "IRRunner.exe /silent",
  "children": [
    {
      "pid": 343686,
      "ppid": 343680,
      "name": "powershell.exe",
      "command": "powershell.exe -NoProfile -WindowStyle Hidden -ExecutionPolicy Bypass -File \"C:\\ProgramData\\Alpine\\Build\\CollectInventory_3914baeb.ps1\" -Host \"SUP-621\" -Mode Verify",
      "children": [
        {
          "pid": 343690,
          "ppid": 343686,
          "name": "timeout.exe",
          "command": "timeout.exe /t 24 /nobreak",
          "children": [
            {
              "pid": 343697,
              "ppid": 343690,
              "name": "bitsadmin.exe",
              "command": "bitsadmin.exe /transfer Jobc08dab1b /download /priority NORMAL \"http://intra-update.corp.local/support/collector.bin\" \"C:\\Users\\neha.rao\\AppData\\Local\\Temp\\agent.cab\"",
              "children": [
                {
                  "pid": 343703,
                  "ppid": 343697,
                  "name": "ping.exe",
                  "command": "ping.exe -n 10 127.0.0.1 > nul",
                  "children": [
                    {
                      "pid": 343710,
                      "ppid": 343703,
                      "name": "whoami.exe",
                      "command": "whoami.exe",
                      "children": [
                        {
                          "pid": 343716,
                          "ppid": 343710,
                          "name": "expand.exe",
                          "command": "expand.exe \"C:\\ProgramData\\Northwind\\Collector\\agent.cab\" -F:* \"C:\\Program Files\\Woodgrove\\Profile\"",
                          "children": [
                            {
                              "pid": 343719,
                              "ppid": 343716,
                              "name": "whoami.exe",
                              "command": "whoami.exe /groups > \"C:\\Users\\neha.rao\\AppData\\Local\\Temp\\who_b4940748.txt\"",
                              "children": [
                                {
                                  "pid": 343725,
                                  "ppid": 343719,
                                  "name": "hostname.exe",
                                  "command": "hostname.exe > \"C:\\Users\\neha.rao\\AppData\\Local\\Temp\\host_672d32f9.txt\"",
                                  "children": [
                                    {
                                      "pid": 343731,
                                      "ppid": 343725,
                                      "name": "regsvr32.exe",
                                      "command": "regsvr32.exe /s /n /i:user \"C:\\Program Files\\Wingtip\\Runtime\\plugin.dll\"",
                                      "children": [
                                        {
                                          "pid": 343738,
                                          "ppid": 343731,
                                          "name": "whoami.exe",
                                          "command": "whoami.exe /all",
                                          "children": [
                                            {
                                              "pid": 343741,
                                              "ppid": 343738,
                                              "name": "msiexec.exe",
                                              "command": "msiexec.exe /i \"C:\\ProgramData\\Contoso\\Updater\\agent.msi\" /qn /l*v \"C:\\ProgramData\\Alpine\\Logs\\msi_a41d7db3.log\"",
                                              "children": [
                                                {
                                                  "pid": 343748,
                                                  "ppid": 343741,
                                                  "name": "powershell.exe",
                                                  "command": "powershell.exe -NoProfile -WindowStyle Hidden -Command \"Start-Sleep -Seconds 17\"",
                                                  "children": [
                                                    {
                                                      "pid": 343752,
                                                      "ppid": 343748,
                                                      "name": "powershell.exe",
                                                      "command": "powershell.exe -NoProfile -WindowStyle Hidden -ExecutionPolicy Bypass -Command \"Get-ComputerInfo | Out-File 'C:\\Users\\neha.rao\\AppData\\Local\\Temp\\sched_13736d41.txt'\"",
                                                      "children": [
                                                        {
                                                          "pid": 343753,
                                                          "ppid": 343752,
                                                          "name": "bitsadmin.exe",
                                                          "command": "bitsadmin.exe /info Job40cd97a8 /verbose",
                                                          "children": [
                                                            {
                                                              "pid": 343757,
                                                              "ppid": 343753,
                                                              "name": "powershell.exe",
                                                              "command": "powershell.exe -NoProfile -WindowStyle Hidden -Command \"Start-Sleep -Seconds 19\"",
                                                              "children": [
                                                                {
                                                                  "pid": 343758,
                                                                  "ppid": 343757,
                                                                  "name": "hostname.exe",
                                                                  "command": "hostname.exe > \"C:\\Users\\neha.rao\\AppData\\Local\\Temp\\host_287ba5bc.txt\"",
                                                                  "children": [
                                                                    {
                                                                      "pid": 343759,
                                                                      "ppid": 343758,
                                                                      "name": "choice.exe",
                                                                      "command": "choice.exe /d y /t 21 > nul",
                                                                      "children": []
                                                                    }
                                                                  ]
                                                                }
                                                              ]
                                                            }
                                                          ]
                                                        },
                                                        {
                                                          "pid": 343762,
                                                          "ppid": 343752,
                                                          "name": "choice.exe",
                                                          "command": "choice.exe /d y /t 17 > nul",
                                                          "children": [
                                                            {
                                                              "pid": 343767,
                                                              "ppid": 343762,
                                                              "name": "bitsadmin.exe",
                                                              "command": "bitsadmin.exe /info Job46b6c8b9 /verbose",
                                                              "children": [
                                                                {
                                                                  "pid": 343772,
                                                                  "ppid": 343767,
                                                                  "name": "hostname.exe",
                                                                  "command": "hostname.exe > \"C:\\Users\\neha.rao\\AppData\\Local\\Temp\\host_a1a390b2.txt\"",
                                                                  "children": [
                                                                    {
                                                                      "pid": 343779,
                                                                      "ppid": 343772,
                                                                      "name": "hostname.exe",
                                                                      "command": "hostname.exe",
                                                                      "children": [
                                                                        {
                                                                          "pid": 343785,
                                                                          "ppid": 343779,
                                                                          "name": "whoami.exe",
                                                                          "command": "whoami.exe > \"C:\\Users\\neha.rao\\AppData\\Local\\Temp\\who_6fe21e14.txt\"",
                                                                          "children": [
                                                                            {
                                                                              "pid": 343786,
                                                                              "ppid": 343785,
                                                                              "name": "whoami.exe",
                                                                              "command": "whoami.exe",
                                                                              "children": []
                                                                            }
                                                                          ]
                                                                        },
                                                                        {
                                                                          "pid": 343787,
                                                                          "ppid": 343779,
                                                                          "name": "hostname.exe",
                                                                          "command": "hostname.exe",
                                                                          "children": [
                                                                            {
                                                                              "pid": 343791,
                                                                              "ppid": 343787,
                                                                              "name": "ping.exe",
                                                                              "command": "ping.exe -n 20 127.0.0.1 > nul",
                                                                              "children": [
                                                                                {
                                                                                  "pid": 343792,
                                                                                  "ppid": 343791,
                                                                                  "name": "hostname.exe",
                                                                                  "command": "hostname.exe",
                                                                                  "children": [
                                                                                    {
                                                                                      "pid": 343795,
                                                                                      "ppid": 343792,
                                                                                      "name": "bitsadmin.exe",
                                                                                      "command": "bitsadmin.exe /info Job51513b04 /verbose",
                                                                                      "children": [
                                                                                        {
                                                                                          "pid": 343797,
                                                                                          "ppid": 343795,
                                                                                          "name": "whoami.exe",
                                                                                          "command": "whoami.exe /priv",
                                                                                          "children": [
                                                                                            {
                                                                                              "pid": 343798,
                                                                                              "ppid": 343797,
                                                                                              "name": "ping.exe",
                                                                                              "command": "ping.exe -n 5 127.0.0.1 > nul",
                                                                                              "children": [
                                                                                                {
                                                                                                  "pid": 343799,
                                                                                                  "ppid": 343798,
                                                                                                  "name": "powershell.exe",
                                                                                                  "command": "powershell.exe -NoProfile -WindowStyle Hidden -Command \"Start-Sleep -Seconds 16\"",
                                                                                                  "children": []
                                                                                                }
                                                                                              ]
                                                                                            }
                                                                                          ]
                                                                                        }
                                                                                      ]
                                                                                    }
                                                                                  ]
                                                                                }
                                                                              ]
                                                                            }
                                                                          ]
                                                                        }
                                                                      ]
                                                                    }
                                                                  ]
                                                                }
                                                              ]
                                                            }
                                                          ]
                                                        }
                                                      ]
                                                    }
                                                  ]
                                                }
                                              ]
                                            }
                                          ]
                                        }
                                      ]
                                    }
                                  ]
                                }
                              ]
                            }
                          ]
                        }
                      ]
                    }
                  ]
                }
              ]
            }
          ]
        }
      ]
    }
  ]
}